setup.py
youda/__init__.py
youda/youdacloud.py
youda.egg-info/PKG-INFO
youda.egg-info/SOURCES.txt
youda.egg-info/dependency_links.txt
youda.egg-info/requires.txt
youda.egg-info/top_level.txt