Metadata-Version: 1.0
Name: youda
Version: 1.0.3
Summary: youdacloud
Home-page: http://www.youda.com.cn
Author: zsd
Author-email: 2758474300@qq.com
License: MIT Licence
Keywords: youda
Platform: any
